shannon/__init__.py
shannon/shannon.py
py_shannon-1.0.1.dist-info/LICENSE
py_shannon-1.0.1.dist-info/METADATA
py_shannon-1.0.1.dist-info/WHEEL
py_shannon-1.0.1.dist-info/top_level.txt
py_shannon-1.0.1.dist-info/RECORD
