Metadata-Version: 2.1
Name: py-shannon
Version: 1.0.1
Summary: Python implementation of the Shannon stream cipher
Home-page: https://github.com/TOPDapp/py-shannon
Author: Kuba Szczodrzyński
Author-email: kuba@szczodrzynski.pl
License: UNKNOWN
Project-URL: Bug Tracker, https://github.com/TOPDapp/py-shannon/issues
Platform: UNKNOWN
Classifier: Programming Language :: Python :: 3
Classifier: License :: OSI Approved :: MIT License
Classifier: Operating System :: OS Independent
Requires-Python: >=3.6
